ezdbx/__init__.py
ezdbx/main.py
ez_dropbox-2.0.5.dist-info/LICENSE
ez_dropbox-2.0.5.dist-info/METADATA
ez_dropbox-2.0.5.dist-info/WHEEL
ez_dropbox-2.0.5.dist-info/top_level.txt
ez_dropbox-2.0.5.dist-info/RECORD
