Metadata-Version: 2.1
Name: ez-dropbox
Version: 2.0.5
Summary: You can easily operate Dropbox!
Home-page: https://github.com/TorDataScientist/ez-dropbox
Author: TorDataScientist
License: MIT License
License-File: LICENSE
Requires-Dist: dropbox
Requires-Dist: tqdm
Requires-Dist: joblib
